pysty/__init__.py
pysty/base.py
pysty/text.py
pysty/buttons/__init__.py
pysty/buttons/default_button.py
pysty/cards/__init__.py
pysty/cards/default_card.py
pysty-0.1.1.dist-info/METADATA
pysty-0.1.1.dist-info/WHEEL
pysty-0.1.1.dist-info/licenses/LICENSE
pysty-0.1.1.dist-info/RECORD
